Metadata-Version: 2.4
Name: llm-fragments-symbex
Version: 0.1
Summary: LLM fragment loader for Python symbols
Author: Simon Willison
License-Expression: Apache-2.0
Project-URL: Homepage, https://github.com/simonw/llm-fragments-symbex
Project-URL: Changelog, https://github.com/simonw/llm-fragments-symbex/releases
Project-URL: Issues, https://github.com/simonw/llm-fragments-symbex/issues
Project-URL: CI, https://github.com/simonw/llm-fragments-symbex/actions
Requires-Python: >=3.9
License-File: LICENSE
Requires-Dist: llm
Requires-Dist: symbex
Provides-Extra: test
Requires-Dist: pytest; extra == "test"
Dynamic: license-file
